idms/__init__.py
idms/functions.py
idms/api/__init__.py
idms/api/contentserver.py
idms-0.2.7.data/data/my_data/data_file
sample/__init__.py
sample/package_data.dat
sample/simple.py
idms-0.2.7.dist-info/LICENSE.txt
idms-0.2.7.dist-info/METADATA
idms-0.2.7.dist-info/WHEEL
idms-0.2.7.dist-info/entry_points.txt
idms-0.2.7.dist-info/top_level.txt
idms-0.2.7.dist-info/RECORD
