Metadata-Version: 2.1
Name: idms
Version: 0.2.7
Summary: Python class to talk to idms REST and Search API, better known as iDMS.
Home-page: https://github.com/Provincie-Zuid-Holland/idms
Author: Daniel Overdevest, Michael de Winter
Author-email: d.overdevest@pzh.nl, mr.de.winter@pzh.nl
Project-URL: Bug Reports, https://github.com/ProvZH/idms/issues
Project-URL: Source, https://github.com/ProvZH/idms
Keywords: idms,contentserver,restapi,searchapi
Classifier: Development Status :: 4 - Beta
Classifier: Intended Audience :: Developers
Classifier: Topic :: Software Development :: Build Tools
Classifier: License :: OSI Approved :: MIT License
Classifier: Programming Language :: Python :: 3
Classifier: Programming Language :: Python :: 3.5
Classifier: Programming Language :: Python :: 3.6
Classifier: Programming Language :: Python :: 3.7
Classifier: Programming Language :: Python :: 3.8
Classifier: Programming Language :: Python :: 3 :: Only
Requires-Python: >=3.5, <4
License-File: LICENSE.txt
Requires-Dist: requests >=2.25.0
Provides-Extra: dev
Requires-Dist: check-manifest ; extra == 'dev'
Requires-Dist: python-dotenv >=0.15.0 ; extra == 'dev'
Requires-Dist: pandas >=1.1.4 ; extra == 'dev'
Requires-Dist: openpyxl ; extra == 'dev'
Provides-Extra: test
Requires-Dist: coverage ; extra == 'test'
